multiLevelPercolation/__init__.py
multiLevelPercolation/multiLevelPercolation.py
multiLevelPercolation/testData.bin
multiLevelPercolation-1.0.0.1.dist-info/LICENSE
multiLevelPercolation-1.0.0.1.dist-info/METADATA
multiLevelPercolation-1.0.0.1.dist-info/WHEEL
multiLevelPercolation-1.0.0.1.dist-info/top_level.txt
multiLevelPercolation-1.0.0.1.dist-info/RECORD
