Metadata-Version: 2.1
Name: multiLevelPercolation
Version: 1.0.0.1
Summary: Identifying individual unique thresholds for structures educed from scalar fields
Home-page: https://github.com/Phoenixfire1081/MultiLevelPercolationAnalysis
Author: Abhishek Harikrishnan
Author-email: abhishek.harikrishnan@fu-berlin.de
License: MIT
Platform: UNKNOWN
Requires-Python: >=3.8
License-File: LICENSE
